ilovejpngs.py
ilovejpngs-0.1.1.dist-info/licenses/LICENSE
ilovejpngs-0.1.1.dist-info/METADATA
ilovejpngs-0.1.1.dist-info/WHEEL
ilovejpngs-0.1.1.dist-info/entry_points.txt
ilovejpngs-0.1.1.dist-info/top_level.txt
ilovejpngs-0.1.1.dist-info/RECORD
