Metadata-Version: 2.4
Name: ilovejpngs
Version: 0.1.1
Summary: A Python library for working with JPEG/PNG images.
Author-email: Simon H-L <Simon@ipconnect.no>
License: MIT
Project-URL: Homepage, https://github.com/Hellestyle/ilovejpngs
Project-URL: Repository, https://github.com/Hellestyle/ilovejpngs
Project-URL: Issues, https://github.com/Hellestyle/ilovejpngs/issues
Keywords: images,jpeg,png
Requires-Python: >=3.10
License-File: LICENSE
Requires-Dist: Pillow>=10.0.0
Dynamic: license-file
